task_priority_summary_verify_utils/__init__.py
task_priority_summary_verify_utils/priority.py
task_priority_summary_verify_utils/summary.py
task_priority_summary_verify_utils/verify.py
task_priority_summary_verify_utils-0.1.dist-info/LICENSE
task_priority_summary_verify_utils-0.1.dist-info/METADATA
task_priority_summary_verify_utils-0.1.dist-info/WHEEL
task_priority_summary_verify_utils-0.1.dist-info/top_level.txt
task_priority_summary_verify_utils-0.1.dist-info/RECORD
