Metadata-Version: 2.1
Name: task_priority_summary_verify_utils
Version: 0.1
Summary: A collection of independent libraries for diff functionalities
Author: Maitreyee
License-File: LICENSE
